pointcyto/data/InMemoryPointCloud.py
pointcyto/data/PointCloud.py
pointcyto/data/__init__.py
pointcyto/data/datamodule.py
pointcyto/data/metadata_base.py
pointcyto/data/metadata_classification.py
pointcyto/data/metadata_regression.py
pointcyto/data/utils.py
pointcyto/io/__init__.py
pointcyto/io/generate_load_data.py
pointcyto/io/meta_read_foldering.py
pointcyto/io/parse_by_ext.py
pointcyto/io/pickle_open_dump.py
pointcyto/io/stitch_path.py
pointcyto/io/utils.py
pointcyto/io/loaders/__init__.py
pointcyto/io/loaders/csv.py
pointcyto/io/loaders/fcs.py
pointcyto/io/loaders/feather.py
pointcyto/io/loaders/jay.py
pointcyto/io/loaders/pt.py
pointcyto/plot/__init__.py
pointcyto/plot/colors.py
pointcyto/testutils/helpers.py
pointcyto/transforms/__init__.py
pointcyto/transforms/transform_param_onlist.py
pointcyto/transforms/transforms.py
pointcyto/transforms/transforms_flowcore.py
pointcyto/transforms/transforms_flowkit.py
pointcyto/transforms/transforms_functional.py
pointcyto/transforms/utils.py
pointcyto-0.0.9.dist-info/LICENSE.txt
pointcyto-0.0.9.dist-info/METADATA
pointcyto-0.0.9.dist-info/WHEEL
pointcyto-0.0.9.dist-info/top_level.txt
pointcyto-0.0.9.dist-info/RECORD
