Metadata-Version: 2.1
Name: pointcyto
Version: 0.0.9
Summary: Add a short description here!
Home-page: https://github.com/pyscaffold/pyscaffold/
Author: gunthergl
Author-email: gunthergl@gmx.net
License: MIT
Project-URL: Documentation, https://pyscaffold.org/
Platform: any
Classifier: Development Status :: 4 - Beta
Classifier: Programming Language :: Python
License-File: LICENSE.txt
Requires-Dist: torch
Requires-Dist: torch-geometric
Requires-Dist: pandas
Requires-Dist: numpy
Requires-Dist: matplotlib
Requires-Dist: pytorch-lightning
Requires-Dist: flowio
Requires-Dist: flowkit
Requires-Dist: datatable
Requires-Dist: importlib-metadata ; python_version < "3.8"
Provides-Extra: testing
Requires-Dist: setuptools ; extra == 'testing'
Requires-Dist: pytest ; extra == 'testing'
Requires-Dist: pytest-cov ; extra == 'testing'
Requires-Dist: pytest-testmon ; extra == 'testing'
Requires-Dist: docstr-coverage ; extra == 'testing'
Requires-Dist: nbsphinx ; extra == 'testing'
Requires-Dist: ipykernel ; extra == 'testing'
Requires-Dist: ipython ; extra == 'testing'
Requires-Dist: wand ; extra == 'testing'
Requires-Dist: pyarrow ; extra == 'testing'
